Household_Account_Book_App/__init__.py
Household_Account_Book_App/main.py
Household_Account_Book_App-0.0.1.dist-info/METADATA
Household_Account_Book_App-0.0.1.dist-info/WHEEL
Household_Account_Book_App-0.0.1.dist-info/entry_points.txt
Household_Account_Book_App-0.0.1.dist-info/top_level.txt
Household_Account_Book_App-0.0.1.dist-info/RECORD
