Metadata-Version: 2.1
Name: Household-Account-Book-App
Version: 0.0.1
Requires-Dist: fastapi
Requires-Dist: pydantic
Requires-Dist: sqlalchemy
Requires-Dist: uvicorn
